sky-excel/__init__.py
sky-excel/main.py
sky-excel/run_main.py
sky-excel/main/__init__.py
sky-excel/main/body_parser.py
sky-excel/main/excel_exporter.py
sky-excel/main/header_parser.py
sky-excel/main/parsed_cell.py
sky-excel/templet/__init__.py
sky-excel/utils/__init__.py
sky-excel/utils/j_config.py
sky-excel/utils/j_dict.py
sky-excel/utils/j_params.py
sky_excel/__init__.py
sky_excel/run_main.py
sky_excel/main/__init__.py
sky_excel/main/body_parser.py
sky_excel/main/excel_exporter.py
sky_excel/main/header_parser.py
sky_excel/main/parsed_cell.py
sky_excel/templet/__init__.py
sky_excel/utils/__init__.py
sky_excel/utils/j_config.py
sky_excel/utils/j_dict.py
sky_excel/utils/j_params.py
xj_excel/__init__.py
xj_excel/run_main.py
xj_excel/main/__init__.py
xj_excel/main/body_parser.py
xj_excel/main/excel_exporter.py
xj_excel/main/header_parser.py
xj_excel/main/parsed_cell.py
xj_excel/templet/__init__.py
xj_excel/utils/__init__.py
xj_excel/utils/j_config.py
xj_excel/utils/j_dict.py
xj_excel/utils/j_params.py
xj_excel-1.0.2.dist-info/METADATA
xj_excel-1.0.2.dist-info/WHEEL
xj_excel-1.0.2.dist-info/top_level.txt
xj_excel-1.0.2.dist-info/RECORD
