Metadata-Version: 2.1
Name: xj-excel
Version: 1.0.2
Summary: excel实验模块
Home-page: UNKNOWN
License: apache 3.0
Platform: UNKNOWN
Requires-Dist: openpyxl
